halospec/__init__.py
halospec/objectives.py
halospec-0.0.3.dist-info/LICENSE
halospec-0.0.3.dist-info/METADATA
halospec-0.0.3.dist-info/WHEEL
halospec-0.0.3.dist-info/top_level.txt
halospec-0.0.3.dist-info/RECORD
